{"title": "P\u0159edseda TOP09 1.1.2018 - odds from tipsport.cz", "resources": [{"schema": {"fields": [{"description": "Date and time (UTC) of retrieving the information", "type": "date", "format": "YYYY-mm-ddTHH:ii:ss.uuuuuu", "name": "date"}, {"description": "Title of the bet/race", "type": "string", "name": "title"}, {"description": "Odds for the result", "type": "number", "name": "odds"}, {"description": "Date of the bet/race", "type": "date", "format": "d.m.Y HH:ii", "name": "date_bet"}, {"description": "Identifier from tipsport.cz", "type": "integer", "name": "identifier"}]}, "langugage": "cs", "path": "odds.csv", "name": "odds"}], "identifier": "2815465", "language": "en", "sources": [{"web": "https://tisport.cz", "name": "Tipsport"}], "description": "Scraped odds from tipsport.cz for: P\u0159edseda TOP09 1.1.2018", "name": "tisport_cz_2815465"}