{"identifier": "2620330", "language": "en", "sources": [{"web": "https://tisport.cz", "name": "Tipsport"}], "description": "Scraped odds from tipsport.cz for: Statut\u00e1rn\u00edm m\u00edstop\u0159edsedou\u010cSSD", "resources": [{"schema": {"fields": [{"description": "Date and time (UTC) of retrieving the information", "type": "date", "format": "YYYY-mm-ddTHH:ii:ss.uuuuuu", "name": "date"}, {"description": "Title of the bet/race", "type": "string", "name": "title"}, {"description": "Odds for the result", "type": "number", "name": "odds"}, {"description": "Date of the bet/race", "type": "date", "format": "d.m.Y HH:ii", "name": "date_bet"}, {"description": "Identifier from tipsport.cz", "type": "integer", "name": "identifier"}]}, "path": "odds.csv", "langugage": "cs", "name": "odds"}], "title": "Statut\u00e1rn\u00edm m\u00edstop\u0159edsedou\u010cSSD - odds from tipsport.cz", "name": "tisport_cz_2620330"}